wisepy2.py
wisepy2-1.4.1.dist-info/LICENSE
wisepy2-1.4.1.dist-info/METADATA
wisepy2-1.4.1.dist-info/WHEEL
wisepy2-1.4.1.dist-info/top_level.txt
wisepy2-1.4.1.dist-info/RECORD
