Metadata-Version: 2.1
Name: wisepy2
Version: 1.4.1
Summary: simple CLI framework
Home-page: https://github.com/Xython/wisepy2
Author: thautwarm
Author-email: twshere@outlook.com
License: MIT
Keywords: CLI solution
Platform: any
Classifier: Programming Language :: Python :: 3.6
Classifier: Programming Language :: Python :: 3.6
Classifier: Programming Language :: Python :: 3.7
Classifier: Programming Language :: Python :: 3.8
Classifier: Programming Language :: Python :: 3.9
Classifier: Programming Language :: Python :: 3.10
Classifier: Programming Language :: Python :: Implementation :: CPython
License-File: LICENSE
